idelucs/LossFunctions.py
idelucs/PytorchUtils.py
idelucs/ResNet.py
idelucs/__init__.py
idelucs/__main__.py
idelucs/cluster.py
idelucs/kmers.cpython-312-darwin.so
idelucs/kmers.pyx
idelucs/models.py
idelucs/utils.py
idelucs/utils_GUI.py
idelucs-1.2.7.dist-info/LICENCE.md
idelucs-1.2.7.dist-info/METADATA
idelucs-1.2.7.dist-info/WHEEL
idelucs-1.2.7.dist-info/entry_points.txt
idelucs-1.2.7.dist-info/top_level.txt
idelucs-1.2.7.dist-info/RECORD
